StoredObjects/__init__.py
StoredObjects/author.py
StoredObjects/department.py
StoredObjects/publication.py
StoredObjects/university.py
kvv_StoredObjects-0.0.16.dist-info/LICENSE
kvv_StoredObjects-0.0.16.dist-info/METADATA
kvv_StoredObjects-0.0.16.dist-info/WHEEL
kvv_StoredObjects-0.0.16.dist-info/top_level.txt
kvv_StoredObjects-0.0.16.dist-info/RECORD
