Metadata-Version: 2.1
Name: kvv-StoredObjects
Version: 0.0.16
Summary: StoredObjects is a helper package with University objects for the Publications Activity Module
Home-page: https://github.com/VladKornilov/StoredObjects
Author: Vladislav Kornilov
Author-email: v.kornilovv@yandex.ru
Project-URL: Bug Tracker, https://github.com/VladKornilov/StoredObjects/issues
Classifier: Programming Language :: Python :: 3
Classifier: License :: OSI Approved :: Apache Software License
Classifier: Operating System :: OS Independent
Requires-Python: >=3.6
License-File: LICENSE
Requires-Dist: requests
Requires-Dist: beautifulsoup4
Requires-Dist: prettytable
